test_cli.py
test_main.py
xlparser/__init__.py
xlparser/cli.py
xlparser/xlparser.py
xlparser-0.6.1.dist-info/LICENSE
xlparser-0.6.1.dist-info/METADATA
xlparser-0.6.1.dist-info/WHEEL
xlparser-0.6.1.dist-info/entry_points.txt
xlparser-0.6.1.dist-info/RECORD
