Metadata-Version: 2.1
Name: xlparser
Version: 0.6.1
Summary: Parse excel(xlsx/xls/csv) to other format(csv, xlsx, json).
License: MIT
Author: ahuigo
Author-email: 1781999+ahuigo@users.noreply.github.com
Requires-Python: >=3.9
Classifier: License :: OSI Approved :: MIT License
Classifier: Programming Language :: Python :: 3
Classifier: Programming Language :: Python :: 3.9
Classifier: Programming Language :: Python :: 3.10
Classifier: Programming Language :: Python :: 3.11
Classifier: Programming Language :: Python :: 3.12
Requires-Dist: click (>=8.1.7,<9.0.0)
Requires-Dist: openpyxl (>=3.1.5,<4.0.0)
Requires-Dist: python-dateutil (>=2.8.2)
Requires-Dist: xlrd (>=2.0.1,<3.0.0)
